flaskmng/__init__.py
flaskmng/__main__.py
flaskmng/utils.py
flaskmng/deploysetup/__init__.py
flaskmng/deploysetup/commands.py
flaskmng/deploysetup/utils.py
flaskmng/removeapp/__init__.py
flaskmng/removeapp/commands.py
flaskmng/removeapp/utils.py
flaskmng/startapp/__init__.py
flaskmng/startapp/commands.py
flaskmng/startapp/utils.py
flaskmng/startproject/__init__.py
flaskmng/startproject/commands.py
flaskmng/startproject/utils.py
flaskmng-1.3.6.dist-info/LICENSE.txt
flaskmng-1.3.6.dist-info/METADATA
flaskmng-1.3.6.dist-info/WHEEL
flaskmng-1.3.6.dist-info/entry_points.txt
flaskmng-1.3.6.dist-info/top_level.txt
flaskmng-1.3.6.dist-info/RECORD
