Metadata-Version: 2.1
Name: flaskmng
Version: 1.3.6
Summary: Tool that makes managing Flask easy.
Home-page: https://github.com/kritibytes/flaskmng#readme
Author: kritibytes
Author-email: kritibytes@gmail.com
License: UNKNOWN
Platform: UNKNOWN
Classifier: Programming Language :: Python :: 3
Classifier: License :: OSI Approved :: MIT License
Classifier: Operating System :: OS Independent
Classifier: Topic :: Software Development
Classifier: Natural Language :: English
Requires-Python: >=3.6
Requires-Dist: click
Requires-Dist: pyfiglet
Requires-Dist: PyInquirer
Requires-Dist: myp
